abaqus_mtx_parser/__init__.py
abaqus_mtx_parser/_version.py
abaqus_mtx_parser/parser.py
abaqus_mtx_parser/mtx/recovery/interface-beam-sub.mtx
abaqus_mtx_parser/mtx/symmetric/inner.mtx
abaqus_mtx_parser/mtx/symmetric/outer.mtx
abaqus_mtx_parser/mtx/symmetric/total.mtx
abaqus_mtx_parser/mtx/unsymmetric/inner.mtx
abaqus_mtx_parser/mtx/unsymmetric/outer.mtx
abaqus_mtx_parser/mtx/unsymmetric/total.mtx
abaqus_mtx_parser-1.1.4.dist-info/LICENSE
abaqus_mtx_parser-1.1.4.dist-info/METADATA
abaqus_mtx_parser-1.1.4.dist-info/WHEEL
abaqus_mtx_parser-1.1.4.dist-info/top_level.txt
abaqus_mtx_parser-1.1.4.dist-info/RECORD
