Metadata-Version: 2.1
Name: abaqus-mtx-parser
Version: 1.1.4
Summary: A python package to parse *.mtx files generated by the keyword *SUBSTRUCTURE MATRIX OUTPUT in Abaqus.
Author-email: HUANG Lihao <huang-lihao@outlook.com>
Project-URL: Homepage, https://github.com/huang-lihao/abaqus-mtx-parser
Project-URL: Bug Tracker, https://github.com/huang-lihao/abaqus-mtx-parser/issues
Classifier: Programming Language :: Python :: 3
Classifier: License :: OSI Approved :: MIT License
Classifier: Operating System :: OS Independent
Requires-Python: >=3.7
License-File: LICENSE
Requires-Dist: numpy
